{
	"conditions": [
		{
			"type": "forge:mod_loaded",
			"modid": "byg"
		},
		{
			"type": "forge:mod_loaded",
			"modid": "tcintegrations"
		}
	],
	"type": "tconstruct:damagable_melting",
	"ingredient": [
		{
			"item": "byg:pendorite_pickaxe"
		},
		{
			"item": "byg:pendorite_axe"
		}
	],
	"result": {
		"fluid": "tcintegrations:pendorite_alloy",
		"amount": 90,
		"unit_size": 10
	},
	"byproducts": [
		{
			"fluid": "tconstruct:molten_netherite",
			"amount": 90,
			"unit_size": 10
		},
		{
			"fluid": "tconstruct:molten_diamond",
			"amount": 300,
			"unit_size": 25
		}
	],
	"temperature": 1250,
	"time": 80
}