{
	"conditions": [
		{
			"type": "forge:mod_loaded",
			"modid": "multitools"
		}
	],
	"type": "tconstruct:damagable_melting",
	"ingredient": {
		"item": "multitools:netherite_multitool"
	},
	"result": {
		"fluid": "tconstruct:molten_netherite",
		"amount": 360,
		"unit_size": 10
	},
	"byproducts": [
		{
			"fluid": "tconstruct:molten_diamond",
			"amount": 900,
			"unit_size": 25
		},
		{
			"fluid": "tconstruct:molten_copper",
			"amount": 90,
			"unit_size": 10
		}
	],
	"temperature": 1250,
	"time": 80
}